riscv_emulator/__init__.py
riscv_emulator/assembler.py
riscv_emulator/debugger.py
riscv_emulator/disassembler.py
riscv_emulator/emulator.py
riscv_emulator/main.py
riscv_emulator-0.1.1.dist-info/licenses/LICENSE
riscv_emulator-0.1.1.dist-info/METADATA
riscv_emulator-0.1.1.dist-info/WHEEL
riscv_emulator-0.1.1.dist-info/entry_points.txt
riscv_emulator-0.1.1.dist-info/top_level.txt
riscv_emulator-0.1.1.dist-info/RECORD
