Metadata-Version: 2.4
Name: riscv-emulator
Version: 0.1.1
Summary: A Python-based RISC-V assembler, emulator, disassembler, and debugger
Author-email: Satvik Malneedi <samalneedi@gmail.com>
License-Expression: MIT
Project-URL: Homepage, https://github.com/sadaveek/riscv-emulator
Requires-Python: >=3.7
License-File: LICENSE
Dynamic: license-file
